[
  {
    "image": "https://study4.com/media/ets2023/img/2/image31.png",
    "audio": "https://study4.com/media/ets2023/audio/ets-test-02-part-1-1.mp3",
    "transcript": "<p><span>(A) A woman is holding a power tool.</span></p><p><span>(B) A woman is opening a drawer.</span></p><p><span>(C) A printer is being unplugged.</span></p><p><span>(D) Office supplies are being put into a box.</span></p>",
    "number": "1",
    "A": "",
    "B": "",
    "C": "",
    "D": "",
    "answer": "B",
    "detail": "<p><span></span></p><p><span>1.</span></p><p><span>(A) M\u1ed9t ng\u01b0\u1eddi ph\u1ee5 n\u1eef \u0111ang c\u1ea7m m\u1ed9t d\u1ee5ng c\u1ee5 \u0111i\u1ec7n c\u1ea7m tay</span></p><p><span>(B) M\u1ed9t ng\u01b0\u1eddi ph\u1ee5 n\u1eef \u0111ang m\u1edf m\u1ed9t ng\u0103n k\u00e9o</span></p><p><span>(C) M\u1ed9t chi\u1ebfc m\u00e1y in \u0111ang \u0111\u01b0\u1ee3c r\u00fat ph\u00edch c\u1eafm</span></p><p><span>(D) V\u0103n ph\u00f2ng ph\u1ea9m \u0111ang \u0111\u01b0\u1ee3c \u0111\u1eb7t v\u00e0o trong m\u1ed9t chi\u1ebfc th\u00f9ng.</span></p>"
  },
  {
    "image": "https://study4.com/media/ets2023/img/2/image2.png",
    "audio": "https://study4.com/media/ets2023/audio/ets-test-02-part-1-2.mp3",
    "transcript": "<p><span>(A) Plants are on top of a cart.</span></p><p><span>(B) A watering can is next to some trees.</span></p><p><span>(C) A man is digging in a garden.</span></p><p><span>(D) A man is near a display of potted plants.</span></p>",
    "number": "2",
    "A": "",
    "B": "",
    "C": "",
    "D": "",
    "answer": "D",
    "detail": "<p><span></span></p><p><span>2.</span></p><p><span>(A) Nh\u1eefng c\u00e1i c\u00e2y \u0111ang \u1edf tr\u00ean c\u00f9ng c\u1ee7a xe \u0111\u1ea9y h\u00e0ng</span></p><p><span>(B) M\u1ed9t b\u00ecnh t\u01b0\u1edbi n\u01b0\u1edbc \u0111ang \u1edf c\u1ea1nh v\u00e0i c\u00e1i c\u00e2y</span></p><p><span>(C) M\u1ed9t ng\u01b0\u1eddi \u0111\u00e0n \u00f4ng \u0111ang \u0111\u00e0o h\u1ed1 trong v\u01b0\u1eddn</span></p><p><span>(D) M\u1ed9t ng\u01b0\u1eddi \u0111\u00e0n \u00f4ng \u0111ang \u1edf c\u1ea1nh khung tr\u01b0ng b\u00e0y nh\u1eefng ch\u1eadu c\u00e2y.</span></p>"
  },
  {
    "image": "https://study4.com/media/ets2023/img/2/image5.png",
    "audio": "https://study4.com/media/ets2023/audio/ets-test-02-part-1-3.mp3",
    "transcript": "<p><span></span></p><p><span>(A) The man is fixing a machine.</span></p><p><span>(B) The man is buying some equipment.</span></p><p><span>(C) The man is lifting a weight.</span></p><p><span>(D) The man is looking at the ceiling.</span></p>",
    "number": "3",
    "A": "",
    "B": "",
    "C": "",
    "D": "",
    "answer": "C",
    "detail": "<p><span></span></p><p><span>3.</span></p><p><span>(A) Ng\u01b0\u1eddi \u0111\u00e0n \u00f4ng \u0111ang s\u1eeda c\u00e1i m\u00e1y</span></p><p><span>(B) Ng\u01b0\u1eddi \u0111\u00e0n \u00f4ng \u0111ang mua m\u1ed9t s\u1ed1 thi\u1ebft b\u1ecb</span></p><p><span>(C) Ng\u01b0\u1eddi \u0111\u00e0n \u00f4ng \u0111ang n\u00e2ng t\u1ea1.</span></p><p><span>(D) Ng\u01b0\u1eddi \u0111\u00e0n \u00f4ng \u0111ang nh\u00ecn l\u00ean tr\u1ea7n nh\u00e0</span></p>"
  },
  {
    "image": "https://study4.com/media/ets2023/img/2/image12.png",
    "audio": "https://study4.com/media/ets2023/audio/ets-test-02-part-1-4.mp3",
    "transcript": "<p><span></span></p><p><span>(A) A wall is decorated with various items.</span></p><p><span>(B) Two chairs are blocking a doorway.</span></p><p><span>(C) A door has been propped open with a statue.</span></p><p><span>(D) A painting is hanging next to a window.</span></p>",
    "number": "4",
    "A": "",
    "B": "",
    "C": "",
    "D": "",
    "answer": "A",
    "detail": "<p><span></span></p><p><span>4.</span></p><p><span>(A) B\u1ee9c t\u01b0\u1eddng \u0111\u01b0\u1ee3c trang tr\u00ed v\u1edbi nhi\u1ec1u m\u00f3n \u0111\u1ed3.</span></p><p><span>(B) Hai chi\u1ebfc gh\u1ebf \u0111ang ch\u1eb7n l\u1ed1i ra v\u00e0o</span></p><p><span>(C) M\u1ed9t c\u00e1nh c\u1eeda \u0111\u01b0\u1ee3c \u0111\u1ec3 m\u1edf ra v\u1edbi m\u1ed9t b\u1ee9c t\u01b0\u1ee3ng</span></p><p><span>(D) M\u1ed9t b\u1ee9c tranh \u0111\u01b0\u1ee3c treo c\u1ea1nh c\u1eeda s\u1ed5</span></p>"
  },
  {
    "image": "https://study4.com/media/ets2023/img/2/image35.png",
    "audio": "https://study4.com/media/ets2023/audio/ets-test-02-part-1-5.mp3",
    "transcript": "<p><span>(A) Some people are browsing in a shop.</span></p><p><span>(B) Some people are exchanging gifts.</span></p><p><span>(C) A customer is paying for some goods.</span></p><p><span>(D) Some salespeople are preparing a display.</span></p><p><span></span></p>",
    "number": "5",
    "A": "",
    "B": "",
    "C": "",
    "D": "",
    "answer": "A",
    "detail": "<p><span>5.</span></p><p><span>(A) M\u1ed9t v\u00e0i ng\u01b0\u1eddi \u0111ang d\u1ea1o quanh trong m\u1ed9t c\u1eeda h\u00e0ng</span></p><p><span>(B) M\u1ed9t v\u00e0i ng\u01b0\u1eddi \u0111ang trao \u0111\u1ed5i nh\u1eefng m\u00f3n qu\u00e0</span></p><p><span>(C) M\u1ed9t kh\u00e1ch h\u00e0ng \u0111ang tr\u1ea3 ti\u1ec1n cho nh\u1eefng m\u00f3n h\u00e0ng</span></p><p><span>(D) M\u1ed9t v\u00e0i nh\u00e2n vi\u00ean kinh doanh \u0111ang chu\u1ea9n b\u1ecb m\u1ed9t k\u1ec7 tr\u01b0ng b\u00e0y.</span></p>"
  },
  {
    "image": "https://study4.com/media/ets2023/img/2/image4.png",
    "audio": "https://study4.com/media/ets2023/audio/ets-test-02-part-1-6.mp3",
    "transcript": "<p><span></span></p><p><span>(A) Cones are blocking access to a road.</span></p><p><span>(B) Some soil is in a pile on the ground.</span></p><p><span>(C) Some bushes have been planted in front of a building.</span></p><p><span>(D) A tree is lying in the roadway.</span></p>",
    "number": "6",
    "A": "",
    "B": "",
    "C": "",
    "D": "",
    "answer": "B",
    "detail": "<p><span></span></p><p><span>6.</span></p><p><span>(A) Nh\u1eefng bi\u1ec3n b\u00e1o h\u00ecnh n\u00f3n \u0111ang ch\u1eb7n l\u1ed1i v\u00e0o m\u1ed9t con \u0111\u01b0\u1eddng.</span></p><p><span>(B) \u0110\u1ea5t \u0111\u01b0\u1ee3c ch\u1ea5t th\u00e0nh \u0111\u1ed1ng tr\u00ean m\u1eb7t \u0111\u1ea5t</span></p><p><span>(C) M\u1ed9t v\u00e0i b\u1ee5i c\u00e2y \u0111\u01b0\u1ee3c tr\u1ed3ng tr\u01b0\u1edbc to\u00e0 nh\u00e0</span></p><p><span>(D) M\u1ed9t c\u00e1i c\u00e2y \u0111ang n\u1eb1m tr\u00ean l\u00f2ng \u0111\u01b0\u1eddng.</span></p>"
  }
]